langchain_oxylabs/__init__.py
langchain_oxylabs/_version.py
langchain_oxylabs/document_loaders.py
langchain_oxylabs/py.typed
langchain_oxylabs/tools.py
langchain_oxylabs/utilities.py
langchain_oxylabs-0.2.0.dist-info/LICENSE
langchain_oxylabs-0.2.0.dist-info/METADATA
langchain_oxylabs-0.2.0.dist-info/WHEEL
langchain_oxylabs-0.2.0.dist-info/RECORD
