Metadata-Version: 2.1
Name: langchain-oxylabs
Version: 0.2.0
Summary: Oxylabs integration package for LangChain
Home-page: https://github.com/oxylabs/langchain-oxylabs
License: MIT
Requires-Python: >=3.9,<4.0
Classifier: License :: OSI Approved :: MIT License
Classifier: Programming Language :: Python :: 3
Classifier: Programming Language :: Python :: 3.9
Classifier: Programming Language :: Python :: 3.10
Classifier: Programming Language :: Python :: 3.11
Classifier: Programming Language :: Python :: 3.12
Classifier: Programming Language :: Python :: 3.13
Requires-Dist: langchain-core (>=0.3.72,<0.4.0)
Requires-Dist: oxylabs (>=2.0.0,<3.0.0)
Project-URL: Repository, https://github.com/oxylabs/langchain-oxylabs
Project-URL: Release Notes, https://github.com/oxylabs/langchain-oxylabs/releases
Project-URL: Source Code, https://github.com/oxylabs/langchain-oxylabs
